Workbook

Sheet Summary
A1: Corporate Carbon Footprint Assessment
A2: =Boundary!B5&" | "&TEXT(Boundary!B6,"yyyy-mm-dd")&" to "&TEXT(Boundary!B7,"yyyy-mm-dd") -> Nordovest Precision Parts S.r.l. (fictional) | 2025-01-01 to 2025-12-31
A4: Headline result | B4: Value | C4: Note
A5: Scope 1 (tCO2e) | B5: =Results!B7 -> 108.032 | C5: Direct emissions: fuels and refrigerants
A6: Scope 2, location-based (tCO2e) | B6: =Results!B8 -> 90.4545 | C6: Italian grid consumption mix
A7: Scope 2, market-based (tCO2e) | B7: =Results!B9 -> 175.905 | C7: National residual mix (proxy)
A8: Scope 3, partial (tCO2e) | B8: =Results!B10 -> 63.0168 | C8: 2 of 15 categories quantified: treat as a floor
A9: Total, location-based (tCO2e) | B9: =Results!B11 -> 261.5033 | C9: Scope 1 + 2 location + 3
A10: Total, market-based (tCO2e) | B10: =Results!B12 -> 346.9538 | C10: Scope 1 + 2 market + 3
A11: Largest source | B11: =INDEX(Results!A21:A41,MATCH(MAX(Results!C21:C41),Results!C21:C41,0)) -> Purchased electricity | C11: Location-based view
A12: Largest source (tCO2e) | B12: =MAX(Results!C21:C41) -> 90.4545
A13: Roadmap: location-based reduction | B13: =Reduction_Scenarios!F16 -> 0.12467284 | C13: Illustrative assumptions
A14: Roadmap: market-based reduction | B14: =Reduction_Scenarios!F17 -> 0.60096578 | C14: Includes renewable electricity
A15: Factor status | B15: =Results!A4 -> NOTE: 3 activity rows use SECONDARY-source factors. Confirm them in the primary file before publishing.
A16: Control status | B16: =Results!B17 -> PASS WITH NOTES | C16: See Controls sheet

Sheet README
A1: Corporate Carbon Footprint Assessment (GHG Protocol)
A2: Fictional case study: Scope 1-2-3 inventory, reduction roadmap and ESG reporting layer
A4: Purpose | B4: Corporate carbon footprint assessment (GHG Protocol) for a fictional manufacturer: inventory, controls, Scope 3 screening, reduction roadmap and ESRS E1 mapping. The model is live: change any blue input and every result updates.
A5: IMPORTANT | B5: All company data in this file is a FICTIONAL EXAMPLE. All emission factors are round PLACEHOLDER numbers, not published values. Replace each one with the real value from a cited source (e.g. DEFRA, ISPRA, AIB residual mix, IPCC) and record the dataset and year. Until you do, the Results sheet shows a warning.
A6: Step 1 | B6: Boundary: set the company, reporting period, consolidation approach and sites.
A7: Step 2 | B7: Emission_Factors: list every factor you use with its unit, source and year. Change Status to VERIFIED only after checking the original source.
A8: Step 3 | B8: Activity_Data: one row per source. Enter quantity, unit and Factor ID. For electricity, enter two rows with the same kWh: one Location, one Market.
A9: Step 4 | B9: Scope3_Screening: go through all 15 categories and record whether each is relevant, with a reason.
A10: Step 5 | B10: Controls: clear every CHECK. Then read Results.
A11: Step 6 | B11: Materiality, ESRS_E1_Map, Data_Governance, Assumptions_Log: complete the ESG layer.
A12: Colour code | B12: Blue text on yellow = cells you edit. Grey with black text = formulas (do not overwrite). Green text = links to another sheet.
A13: Data quality scale | B13: 1 = metered or invoiced data; 2 = records from a reliable system; 3 = partly estimated; 4 = mostly estimated or extrapolated; 5 = rough proxy. Define your own scale in Assumptions_Log if you change it.
A14: Units | B14: Emission factors are in kg CO2e per unit. Emissions are shown in tonnes CO2e (kg / 1000). The unit in Activity_Data must match the unit of the factor.
A15: Regulatory note | B15: ESRS and CSRD scope and timelines are being revised under the EU Omnibus simplification. Check the current text before relying on the ESRS_E1_Map.
A16: Sheets | B16: Boundary | Activity_Data | Emission_Factors | Results | Scope3_Screening | Controls | Materiality | ESRS_E1_Map | Data_Governance | Assumptions_Log | Lists (dropdown values)

Sheet Boundary
A1: Organisational and operational boundary
A2: Define what is inside the inventory before collecting data
A4: Parameter | B4: Value | C4: Guidance
A5: Company / entity | B5: Nordovest Precision Parts S.r.l. (fictional) | C5: Legal entity or group being reported.
A6: Reporting period start | B6: 45658 | C6: Usually a full calendar or financial year.
A7: Reporting period end | B7: 46022
A8: Base year | B8: 2025 | C8: Year against which future reductions are measured.
A9: Consolidation approach | B9: Operational control | C9: Operational control, financial control or equity share. Apply it consistently.
A10: Gases covered | B10: CO2, CH4, N2O, HFCs | C10: State which of the Kyoto gases are included.
A11: GWP source | B11: IPCC AR5, 100-year (CH4 = 28, N2O = 265) | C11: State the report and time horizon used to convert gases to CO2e.
A12: Emission factor sources | B12: ISPRA 430/2026; DESNZ/DEFRA 2026; IPCC AR5 (see Emission_Factors) | C12: List the databases used. Details go in Emission_Factors.
A15: Site / entity | B15: Country | C15: Activity | D15: Included? (Yes/No) | E15: Rationale if excluded
A16: HQ Milan | B16: Italy | C16: Offices | D16: Yes
A17: Plant 1 | B17: Italy | C17: Manufacturing | D17: Yes
A26: Exclusions and limitations
A27: Scope 3 categories 1, 3, 4 and 5 are relevant but not quantified in this version (see Scope3_Screening).
A28: Categories 8, 11, 13, 14 and 15 are judged not relevant for this business; rationale in Scope3_Screening.
A29: Fuel factors cover CO2 only; CH4 and N2O from combustion are not included. No process emissions or biogenic CO2 sources are assumed.
A30: Both sites are within the operational-control boundary; no joint ventures or leased-out assets.

Sheet Activity_Data
A1: Activity data and emissions
A2: Blue on yellow = enter data. Grey = formulas. Scope 2: enter one Location row and one Market row with the same kWh.
A5: Row ID | B5: Scope (1/2/3) | C5: Category | D5: Description | E5: Site / entity | F5: Quantity | G5: Unit | H5: Factor ID | I5: Scope 2 method | J5: Factor (kg CO2e / unit) | K5: Emissions (tCO2e) | L5: Data source / owner | M5: Data quality (1-5) | N5: Check | O5: Notes
A6: A-001 | B6: 1 | C6: Mobile combustion | D6: Diesel for fleet and generator (from delivery notes) | E6: HQ Milan | F6: 10 | G6: tonne | H6: EF-001 | J6: =IF(H6="","",IFERROR(INDEX(Emission_Factors!$D$6:$D$55,MATCH(H6,Emission_Factors!$A$6:$A$55,0)),"")) -> 3186 | K6: =IF(OR(F6="",J6=""),0,F6*J6/1000) -> 31.86 | L6: Fuel delivery notes (Fleet manager) | M6: 2 | N6: =IF(F6="","",IF(H6="","NO FACTOR",IF(ISNA(MATCH(H6,Emission_Factors!$A$6:$A$55,0)),"BAD FACTOR ID",IF(INDEX(Emission_Factors!$C$6:$C$55,MATCH(H6,Emission_Factors!$A$6:$A$55,0))<>G6,"UNIT MISMATCH",IF(AND(B6=2,I6=""),"MISSING S2 METHOD",IF(OR(L6="",M6=""),"MISSING SOURCE/DQ","OK")))))) -> OK | O6: Fictional data for illustration.
A7: A-002 | B7: 1 | C7: Stationary combustion | D7: Natural gas for boilers | E7: Plant 1 | F7: 30000 | G7: m3 | H7: EF-002 | J7: =IF(H7="","",IFERROR(INDEX(Emission_Factors!$D$6:$D$55,MATCH(H7,Emission_Factors!$A$6:$A$55,0)),"")) -> 2.026 | K7: =IF(OR(F7="",J7=""),0,F7*J7/1000) -> 60.78 | L7: Utility invoices (Facilities) | M7: 1 | N7: =IF(F7="","",IF(H7="","NO FACTOR",IF(ISNA(MATCH(H7,Emission_Factors!$A$6:$A$55,0)),"BAD FACTOR ID",IF(INDEX(Emission_Factors!$C$6:$C$55,MATCH(H7,Emission_Factors!$A$6:$A$55,0))<>G7,"UNIT MISMATCH",IF(AND(B7=2,I7=""),"MISSING S2 METHOD",IF(OR(L7="",M7=""),"MISSING SOURCE/DQ","OK")))))) -> OK | O7: Fictional data for illustration.
A8: A-003 | B8: 1 | C8: Fugitive emissions (refrigerants) | D8: R410A top-up in chillers | E8: Plant 1 | F8: 8 | G8: kg | H8: EF-003 | J8: =IF(H8="","",IFERROR(INDEX(Emission_Factors!$D$6:$D$55,MATCH(H8,Emission_Factors!$A$6:$A$55,0)),"")) -> 1924 | K8: =IF(OR(F8="",J8=""),0,F8*J8/1000) -> 15.392 | L8: Maintenance log (Facilities) | M8: 2 | N8: =IF(F8="","",IF(H8="","NO FACTOR",IF(ISNA(MATCH(H8,Emission_Factors!$A$6:$A$55,0)),"BAD FACTOR ID",IF(INDEX(Emission_Factors!$C$6:$C$55,MATCH(H8,Emission_Factors!$A$6:$A$55,0))<>G8,"UNIT MISMATCH",IF(AND(B8=2,I8=""),"MISSING S2 METHOD",IF(OR(L8="",M8=""),"MISSING SOURCE/DQ","OK")))))) -> OK | O8: Fictional data for illustration.
A9: A-004 | B9: 2 | C9: Purchased electricity | D9: Grid electricity | E9: Plant 1 | F9: 450000 | G9: kWh | H9: EF-004 | I9: Location | J9: =IF(H9="","",IFERROR(INDEX(Emission_Factors!$D$6:$D$55,MATCH(H9,Emission_Factors!$A$6:$A$55,0)),"")) -> 0.20101 | K9: =IF(OR(F9="",J9=""),0,F9*J9/1000) -> 90.4545 | L9: Utility invoices (Facilities) | M9: 1 | N9: =IF(F9="","",IF(H9="","NO FACTOR",IF(ISNA(MATCH(H9,Emission_Factors!$A$6:$A$55,0)),"BAD FACTOR ID",IF(INDEX(Emission_Factors!$C$6:$C$55,MATCH(H9,Emission_Factors!$A$6:$A$55,0))<>G9,"UNIT MISMATCH",IF(AND(B9=2,I9=""),"MISSING S2 METHOD",IF(OR(L9="",M9=""),"MISSING SOURCE/DQ","OK")))))) -> OK | O9: Fictional data for illustration.
A10: A-005 | B10: 2 | C10: Purchased electricity | D10: Grid electricity | E10: Plant 1 | F10: 450000 | G10: kWh | H10: EF-005 | I10: Market | J10: =IF(H10="","",IFERROR(INDEX(Emission_Factors!$D$6:$D$55,MATCH(H10,Emission_Factors!$A$6:$A$55,0)),"")) -> 0.3909 | K10: =IF(OR(F10="",J10=""),0,F10*J10/1000) -> 175.905 | L10: Utility invoices (Facilities) | M10: 1 | N10: =IF(F10="","",IF(H10="","NO FACTOR",IF(ISNA(MATCH(H10,Emission_Factors!$A$6:$A$55,0)),"BAD FACTOR ID",IF(INDEX(Emission_Factors!$C$6:$C$55,MATCH(H10,Emission_Factors!$A$6:$A$55,0))<>G10,"UNIT MISMATCH",IF(AND(B10=2,I10=""),"MISSING S2 METHOD",IF(OR(L10="",M10=""),"MISSING SOURCE/DQ","OK")))))) -> OK | O10: Fictional data for illustration.
A11: A-006 | B11: 3 | C11: 6. Business travel | D11: Air travel, short-haul economy | E11: Group | F11: 180000 | G11: pkm | H11: EF-006 | J11: =IF(H11="","",IFERROR(INDEX(Emission_Factors!$D$6:$D$55,MATCH(H11,Emission_Factors!$A$6:$A$55,0)),"")) -> 0.12576 | K11: =IF(OR(F11="",J11=""),0,F11*J11/1000) -> 22.6368 | L11: Travel agency report (HR) | M11: 2 | N11: =IF(F11="","",IF(H11="","NO FACTOR",IF(ISNA(MATCH(H11,Emission_Factors!$A$6:$A$55,0)),"BAD FACTOR ID",IF(INDEX(Emission_Factors!$C$6:$C$55,MATCH(H11,Emission_Factors!$A$6:$A$55,0))<>G11,"UNIT MISMATCH",IF(AND(B11=2,I11=""),"MISSING S2 METHOD",IF(OR(L11="",M11=""),"MISSING SOURCE/DQ","OK")))))) -> OK | O11: Fictional data for illustration.
A12: A-007 | B12: 3 | C12: 7. Employee commuting | D12: Commuting by car (survey-based) | E12: Group | F12: 250000 | G12: km | H12: EF-007 | J12: =IF(H12="","",IFERROR(INDEX(Emission_Factors!$D$6:$D$55,MATCH(H12,Emission_Factors!$A$6:$A$55,0)),"")) -> 0.16152 | K12: =IF(OR(F12="",J12=""),0,F12*J12/1000) -> 40.38 | L12: Employee survey (HR), extrapolated | M12: 4 | N12: =IF(F12="","",IF(H12="","NO FACTOR",IF(ISNA(MATCH(H12,Emission_Factors!$A$6:$A$55,0)),"BAD FACTOR ID",IF(INDEX(Emission_Factors!$C$6:$C$55,MATCH(H12,Emission_Factors!$A$6:$A$55,0))<>G12,"UNIT MISMATCH",IF(AND(B12=2,I12=""),"MISSING S2 METHOD",IF(OR(L12="",M12=""),"MISSING SOURCE/DQ","OK")))))) -> OK | O12: Fictional data for illustration.
A13: A-008 | J13: =IF(H13="","",IFERROR(INDEX(Emission_Factors!$D$6:$D$55,MATCH(H13,Emission_Factors!$A$6:$A$55,0)),"")) | K13: =IF(OR(F13="",J13=""),0,F13*J13/1000) -> 0 | N13: =IF(F13="","",IF(H13="","NO FACTOR",IF(ISNA(MATCH(H13,Emission_Factors!$A$6:$A$55,0)),"BAD FACTOR ID",IF(INDEX(Emission_Factors!$C$6:$C$55,MATCH(H13,Emission_Factors!$A$6:$A$55,0))<>G13,"UNIT MISMATCH",IF(AND(B13=2,I13=""),"MISSING S2 METHOD",IF(OR(L13="",M13=""),"MISSING SOURCE/DQ","OK"))))))
A14: A-009 | J14: =IF(H14="","",IFERROR(INDEX(Emission_Factors!$D$6:$D$55,MATCH(H14,Emission_Factors!$A$6:$A$55,0)),"")) | K14: =IF(OR(F14="",J14=""),0,F14*J14/1000) -> 0 | N14: =IF(F14="","",IF(H14="","NO FACTOR",IF(ISNA(MATCH(H14,Emission_Factors!$A$6:$A$55,0)),"BAD FACTOR ID",IF(INDEX(Emission_Factors!$C$6:$C$55,MATCH(H14,Emission_Factors!$A$6:$A$55,0))<>G14,"UNIT MISMATCH",IF(AND(B14=2,I14=""),"MISSING S2 METHOD",IF(OR(L14="",M14=""),"MISSING SOURCE/DQ","OK"))))))
A15: A-010 | J15: =IF(H15="","",IFERROR(INDEX(Emission_Factors!$D$6:$D$55,MATCH(H15,Emission_Factors!$A$6:$A$55,0)),"")) | K15: =IF(OR(F15="",J15=""),0,F15*J15/1000) -> 0 | N15: =IF(F15="","",IF(H15="","NO FACTOR",IF(ISNA(MATCH(H15,Emission_Factors!$A$6:$A$55,0)),"BAD FACTOR ID",IF(INDEX(Emission_Factors!$C$6:$C$55,MATCH(H15,Emission_Factors!$A$6:$A$55,0))<>G15,"UNIT MISMATCH",IF(AND(B15=2,I15=""),"MISSING S2 METHOD",IF(OR(L15="",M15=""),"MISSING SOURCE/DQ","OK"))))))
A16: A-011 | J16: =IF(H16="","",IFERROR(INDEX(Emission_Factors!$D$6:$D$55,MATCH(H16,Emission_Factors!$A$6:$A$55,0)),"")) | K16: =IF(OR(F16="",J16=""),0,F16*J16/1000) -> 0 | N16: =IF(F16="","",IF(H16="","NO FACTOR",IF(ISNA(MATCH(H16,Emission_Factors!$A$6:$A$55,0)),"BAD FACTOR ID",IF(INDEX(Emission_Factors!$C$6:$C$55,MATCH(H16,Emission_Factors!$A$6:$A$55,0))<>G16,"UNIT MISMATCH",IF(AND(B16=2,I16=""),"MISSING S2 METHOD",IF(OR(L16="",M16=""),"MISSING SOURCE/DQ","OK"))))))
A17: A-012 | J17: =IF(H17="","",IFERROR(INDEX(Emission_Factors!$D$6:$D$55,MATCH(H17,Emission_Factors!$A$6:$A$55,0)),"")) | K17: =IF(OR(F17="",J17=""),0,F17*J17/1000) -> 0 | N17: =IF(F17="","",IF(H17="","NO FACTOR",IF(ISNA(MATCH(H17,Emission_Factors!$A$6:$A$55,0)),"BAD FACTOR ID",IF(INDEX(Emission_Factors!$C$6:$C$55,MATCH(H17,Emission_Factors!$A$6:$A$55,0))<>G17,"UNIT MISMATCH",IF(AND(B17=2,I17=""),"MISSING S2 METHOD",IF(OR(L17="",M17=""),"MISSING SOURCE/DQ","OK"))))))
A18: A-013 | J18: =IF(H18="","",IFERROR(INDEX(Emission_Factors!$D$6:$D$55,MATCH(H18,Emission_Factors!$A$6:$A$55,0)),"")) | K18: =IF(OR(F18="",J18=""),0,F18*J18/1000) -> 0 | N18: =IF(F18="","",IF(H18="","NO FACTOR",IF(ISNA(MATCH(H18,Emission_Factors!$A$6:$A$55,0)),"BAD FACTOR ID",IF(INDEX(Emission_Factors!$C$6:$C$55,MATCH(H18,Emission_Factors!$A$6:$A$55,0))<>G18,"UNIT MISMATCH",IF(AND(B18=2,I18=""),"MISSING S2 METHOD",IF(OR(L18="",M18=""),"MISSING SOURCE/DQ","OK"))))))
A19: A-014 | J19: =IF(H19="","",IFERROR(INDEX(Emission_Factors!$D$6:$D$55,MATCH(H19,Emission_Factors!$A$6:$A$55,0)),"")) | K19: =IF(OR(F19="",J19=""),0,F19*J19/1000) -> 0 | N19: =IF(F19="","",IF(H19="","NO FACTOR",IF(ISNA(MATCH(H19,Emission_Factors!$A$6:$A$55,0)),"BAD FACTOR ID",IF(INDEX(Emission_Factors!$C$6:$C$55,MATCH(H19,Emission_Factors!$A$6:$A$55,0))<>G19,"UNIT MISMATCH",IF(AND(B19=2,I19=""),"MISSING S2 METHOD",IF(OR(L19="",M19=""),"MISSING SOURCE/DQ","OK"))))))
A20: A-015 | J20: =IF(H20="","",IFERROR(INDEX(Emission_Factors!$D$6:$D$55,MATCH(H20,Emission_Factors!$A$6:$A$55,0)),"")) | K20: =IF(OR(F20="",J20=""),0,F20*J20/1000) -> 0 | N20: =IF(F20="","",IF(H20="","NO FACTOR",IF(ISNA(MATCH(H20,Emission_Factors!$A$6:$A$55,0)),"BAD FACTOR ID",IF(INDEX(Emission_Factors!$C$6:$C$55,MATCH(H20,Emission_Factors!$A$6:$A$55,0))<>G20,"UNIT MISMATCH",IF(AND(B20=2,I20=""),"MISSING S2 METHOD",IF(OR(L20="",M20=""),"MISSING SOURCE/DQ","OK"))))))
A21: A-016 | J21: =IF(H21="","",IFERROR(INDEX(Emission_Factors!$D$6:$D$55,MATCH(H21,Emission_Factors!$A$6:$A$55,0)),"")) | K21: =IF(OR(F21="",J21=""),0,F21*J21/1000) -> 0 | N21: =IF(F21="","",IF(H21="","NO FACTOR",IF(ISNA(MATCH(H21,Emission_Factors!$A$6:$A$55,0)),"BAD FACTOR ID",IF(INDEX(Emission_Factors!$C$6:$C$55,MATCH(H21,Emission_Factors!$A$6:$A$55,0))<>G21,"UNIT MISMATCH",IF(AND(B21=2,I21=""),"MISSING S2 METHOD",IF(OR(L21="",M21=""),"MISSING SOURCE/DQ","OK"))))))
A22: A-017 | J22: =IF(H22="","",IFERROR(INDEX(Emission_Factors!$D$6:$D$55,MATCH(H22,Emission_Factors!$A$6:$A$55,0)),"")) | K22: =IF(OR(F22="",J22=""),0,F22*J22/1000) -> 0 | N22: =IF(F22="","",IF(H22="","NO FACTOR",IF(ISNA(MATCH(H22,Emission_Factors!$A$6:$A$55,0)),"BAD FACTOR ID",IF(INDEX(Emission_Factors!$C$6:$C$55,MATCH(H22,Emission_Factors!$A$6:$A$55,0))<>G22,"UNIT MISMATCH",IF(AND(B22=2,I22=""),"MISSING S2 METHOD",IF(OR(L22="",M22=""),"MISSING SOURCE/DQ","OK"))))))
A23: A-018 | J23: =IF(H23="","",IFERROR(INDEX(Emission_Factors!$D$6:$D$55,MATCH(H23,Emission_Factors!$A$6:$A$55,0)),"")) | K23: =IF(OR(F23="",J23=""),0,F23*J23/1000) -> 0 | N23: =IF(F23="","",IF(H23="","NO FACTOR",IF(ISNA(MATCH(H23,Emission_Factors!$A$6:$A$55,0)),"BAD FACTOR ID",IF(INDEX(Emission_Factors!$C$6:$C$55,MATCH(H23,Emission_Factors!$A$6:$A$55,0))<>G23,"UNIT MISMATCH",IF(AND(B23=2,I23=""),"MISSING S2 METHOD",IF(OR(L23="",M23=""),"MISSING SOURCE/DQ","OK"))))))
A24: A-019 | J24: =IF(H24="","",IFERROR(INDEX(Emission_Factors!$D$6:$D$55,MATCH(H24,Emission_Factors!$A$6:$A$55,0)),"")) | K24: =IF(OR(F24="",J24=""),0,F24*J24/1000) -> 0 | N24: =IF(F24="","",IF(H24="","NO FACTOR",IF(ISNA(MATCH(H24,Emission_Factors!$A$6:$A$55,0)),"BAD FACTOR ID",IF(INDEX(Emission_Factors!$C$6:$C$55,MATCH(H24,Emission_Factors!$A$6:$A$55,0))<>G24,"UNIT MISMATCH",IF(AND(B24=2,I24=""),"MISSING S2 METHOD",IF(OR(L24="",M24=""),"MISSING SOURCE/DQ","OK"))))))
... A45: A-040 | J45: =IF(H45="","",IFERROR(INDEX(Emission_Factors!$D$6:$D$55,MATCH(H45,Emission_Factors!$A$6:$A$55,0)),"")) | K45: =IF(OR(F45="",J45=""),0,F45*J45/1000) -> 0 | N45: =IF(F45="","",IF(H45="","NO FACTOR",IF(ISNA(MATCH(H45,Emission_Factors!$A$6:$A$55,0)),"BAD FACTOR ID",IF(INDEX(Emission_Factors!$C$6:$C$55,MATCH(H45,Emission_Factors!$A$6:$A$55,0))<>G45,"UNIT MISMATCH",IF(AND(B45=2,I45=""),"MISSING S2 METHOD",IF(OR(L45="",M45=""),"MISSING SOURCE/DQ","OK"))))))

Sheet Emission_Factors
A1: Emission factor library
A2: kg CO2e per unit. Every factor needs a source, a year and a status (VERIFIED / SECONDARY / PLACEHOLDER).
A5: Factor ID | B5: Description | C5: Unit | D5: Factor (kg CO2e / unit) | E5: Source (publisher + dataset) | F5: Year | G5: Status | H5: Notes
A6: EF-001 | B6: Diesel (gasolio), stationary and mobile combustion, CO2 only | C6: tonne | D6: 3186 | E6: ISPRA Rapporti 430/2026, Table 1.4 (IPCC 2006 default, 3.186 tCO2/t) | F6: 2006 | G6: VERIFIED | H6: CO2 only; CH4 and N2O not included. https://www.isprambiente.gov.it/files2026/pubblicazioni/rapporti/r430-2026-2.pdf
A7: EF-002 | B7: Natural gas, stationary combustion, CO2 only | C7: m3 | D7: 2.026 | E7: ISPRA Rapporti 430/2026, Table 1.4 (2.026 tCO2 per 1000 Sm3) | F7: 2024 | G7: VERIFIED | H7: CO2 only; national fuel EF for 2024 (latest final year). Sm3 taken as m3.
A8: EF-003 | B8: Refrigerant R-410A leakage (GWP-weighted) | C8: kg | D8: 1924 | E8: IPCC AR5 100-year GWP, as stated in Arkema Forane 410A datasheet | F8: 2013 | G8: SECONDARY | H8: Confirm against IPCC AR5 WG1 Ch.8 Appendix (HFC-32 and HFC-125 GWPs) or EU F-gas regulation (AR4-based value is different).
A9: EF-004 | B9: Italian grid electricity, location-based (consumption mix, GHG) | C9: kWh | D9: 0.20101 | E9: ISPRA Rapporti 430/2026, Table 1.18 (201.01 g CO2e/kWh) | F9: 2025 | G9: VERIFIED | H9: 2025 value is PRELIMINARY; ISPRA publishes the final value in the next edition.
A10: EF-005 | B10: Italian residual mix, market-based proxy (CO2) | C10: kWh | D10: 0.3909 | E10: ISPRA Rapporti 430/2026, section 1.3 (residual mix 390.9 g CO2/kWh) | F10: 2025 | G10: VERIFIED | H10: Preliminary, CO2 only, production basis. Not the AIB European Residual Mix: replace with AIB value if required.
A11: EF-006 | B11: Air travel, short-haul, economy, with radiative forcing | C11: pkm | D11: 0.12576 | E11: DESNZ/DEFRA 2026, sheet 'Business travel- air', cell E25 (via greencalculus.com and carbonpass.co) | F11: 2026 | G11: SECONDARY | H11: UK-based factor; confirm in the official 2026 full-set spreadsheet on GOV.UK.
A12: EF-007 | B12: Passenger car, average petrol, engine size unknown | C12: km | D12: 0.16152 | E12: DESNZ/DEFRA 2026, sheet 'Business travel- land' (via greencalculus.com) | F12: 2026 | G12: SECONDARY | H12: Per vehicle-km, not per passenger-km. Confirm in the official 2026 full-set spreadsheet.

Sheet Results
A1: Results: GHG inventory summary
A2: ="Company: "&Boundary!B5&" | Period: "&TEXT(Boundary!B6,"yyyy-mm-dd")&" to "&TEXT(Boundary!B7,"yyyy-mm-dd") -> Company: Nordovest Precision Parts S.r.l. (fictional) | Period: 2025-01-01 to 2025-12-31
A4: =IF(Controls!C11>0,"WARNING: "&Controls!C11&" activity rows use PLACEHOLDER factors. Results are illustrative only.",IF(Controls!C12>0,"NOTE: "&Controls!C12&" activity rows use SECONDARY-source factors. Confirm them in the primary file before publishing.","All emission factors in use are VERIFIED against primary sources.")) -> NOTE: 3 activity rows use SECONDARY-source factors. Confirm them in the primary file before publishing.
A6: Metric | B6: tCO2e | C6: % of location-based total | D6: % of market-based total
A7: Scope 1 (direct) | B7: =SUMIFS(Activity_Data!$K$6:$K$45,Activity_Data!$B$6:$B$45,1) -> 108.032 | C7: =IF($B$11=0,0,B7/$B$11) -> 0.41311907 | D7: =IF($B$12=0,0,B7/$B$12) -> 0.31137287
A8: Scope 2, location-based | B8: =SUMIFS(Activity_Data!$K$6:$K$45,Activity_Data!$B$6:$B$45,2,Activity_Data!$I$6:$I$45,"Location") -> 90.4545 | C8: =IF($B$11=0,0,B8/$B$11) -> 0.34590194
A9: Scope 2, market-based | B9: =SUMIFS(Activity_Data!$K$6:$K$45,Activity_Data!$B$6:$B$45,2,Activity_Data!$I$6:$I$45,"Market") -> 175.905 | D9: =IF($B$12=0,0,B9/$B$12) -> 0.50699834
A10: Scope 3 (value chain) | B10: =SUMIFS(Activity_Data!$K$6:$K$45,Activity_Data!$B$6:$B$45,3) -> 63.0168 | C10: =IF($B$11=0,0,B10/$B$11) -> 0.24097899 | D10: =IF($B$12=0,0,B10/$B$12) -> 0.18162879
A11: Total, location-based (Scope 1 + 2L + 3) | B11: =B7+B8+B10 -> 261.5033
A12: Total, market-based (Scope 1 + 2M + 3) | B12: =B7+B9+B10 -> 346.9538
A14: Emissions-weighted data quality (1 = best, 5 = weakest) | B14: =IFERROR(SUMPRODUCT(Activity_Data!$K$6:$K$45,Activity_Data!$M$6:$M$45)/SUM(Activity_Data!$K$6:$K$45),"n/a") -> 1.4367288
A15: Open row-level check flags | B15: =SUM(Controls!C6:C10) -> 0
A16: Scope 3 categories marked relevant but not quantified | B16: =COUNTIFS(Scope3_Screening!$B$6:$B$20,"Yes",Scope3_Screening!$F$6:$F$20,"No") -> 4
A17: Overall control status | B17: =Controls!D19 -> PASS WITH NOTES
A20: Category | B20: Scope | C20: tCO2e (Scope 2 location-based) | D20: % of location-based total
A21: =Lists!A1 -> Stationary combustion | B21: 1 | C21: =SUMIFS(Activity_Data!$K$6:$K$45,Activity_Data!$C$6:$C$45,A21,Activity_Data!$I$6:$I$45,"<>Market") -> 60.78 | D21: =IF($B$11=0,0,C21/$B$11) -> 0.23242537
A22: =Lists!A2 -> Mobile combustion | B22: 1 | C22: =SUMIFS(Activity_Data!$K$6:$K$45,Activity_Data!$C$6:$C$45,A22,Activity_Data!$I$6:$I$45,"<>Market") -> 31.86 | D22: =IF($B$11=0,0,C22/$B$11) -> 0.12183403
A23: =Lists!A3 -> Fugitive emissions (refrigerants) | B23: 1 | C23: =SUMIFS(Activity_Data!$K$6:$K$45,Activity_Data!$C$6:$C$45,A23,Activity_Data!$I$6:$I$45,"<>Market") -> 15.392 | D23: =IF($B$11=0,0,C23/$B$11) -> 0.058859678
A24: =Lists!A4 -> Process emissions | B24: 1 | C24: =SUMIFS(Activity_Data!$K$6:$K$45,Activity_Data!$C$6:$C$45,A24,Activity_Data!$I$6:$I$45,"<>Market") -> 0 | D24: =IF($B$11=0,0,C24/$B$11) -> 0
A25: =Lists!A5 -> Purchased electricity | B25: 2 | C25: =SUMIFS(Activity_Data!$K$6:$K$45,Activity_Data!$C$6:$C$45,A25,Activity_Data!$I$6:$I$45,"<>Market") -> 90.4545 | D25: =IF($B$11=0,0,C25/$B$11) -> 0.34590194
A26: =Lists!A6 -> Purchased heat, steam and cooling | B26: 2 | C26: =SUMIFS(Activity_Data!$K$6:$K$45,Activity_Data!$C$6:$C$45,A26,Activity_Data!$I$6:$I$45,"<>Market") -> 0 | D26: =IF($B$11=0,0,C26/$B$11) -> 0
A27: =Lists!A7 -> 1. Purchased goods and services | B27: 3 | C27: =SUMIFS(Activity_Data!$K$6:$K$45,Activity_Data!$C$6:$C$45,A27,Activity_Data!$I$6:$I$45,"<>Market") -> 0 | D27: =IF($B$11=0,0,C27/$B$11) -> 0
A28: =Lists!A8 -> 2. Capital goods | B28: 3 | C28: =SUMIFS(Activity_Data!$K$6:$K$45,Activity_Data!$C$6:$C$45,A28,Activity_Data!$I$6:$I$45,"<>Market") -> 0 | D28: =IF($B$11=0,0,C28/$B$11) -> 0
A29: =Lists!A9 -> 3. Fuel- and energy-related activities | B29: 3 | C29: =SUMIFS(Activity_Data!$K$6:$K$45,Activity_Data!$C$6:$C$45,A29,Activity_Data!$I$6:$I$45,"<>Market") -> 0 | D29: =IF($B$11=0,0,C29/$B$11) -> 0
A30: =Lists!A10 -> 4. Upstream transportation and distribution | B30: 3 | C30: =SUMIFS(Activity_Data!$K$6:$K$45,Activity_Data!$C$6:$C$45,A30,Activity_Data!$I$6:$I$45,"<>Market") -> 0 | D30: =IF($B$11=0,0,C30/$B$11) -> 0
A31: =Lists!A11 -> 5. Waste generated in operations | B31: 3 | C31: =SUMIFS(Activity_Data!$K$6:$K$45,Activity_Data!$C$6:$C$45,A31,Activity_Data!$I$6:$I$45,"<>Market") -> 0 | D31: =IF($B$11=0,0,C31/$B$11) -> 0
A32: =Lists!A12 -> 6. Business travel | B32: 3 | C32: =SUMIFS(Activity_Data!$K$6:$K$45,Activity_Data!$C$6:$C$45,A32,Activity_Data!$I$6:$I$45,"<>Market") -> 22.6368 | D32: =IF($B$11=0,0,C32/$B$11) -> 0.086564108
... A41: =Lists!A21 -> 15. Investments | B41: 3 | C41: =SUMIFS(Activity_Data!$K$6:$K$45,Activity_Data!$C$6:$C$45,A41,Activity_Data!$I$6:$I$45,"<>Market") -> 0 | D41: =IF($B$11=0,0,C41/$B$11) -> 0
A42: Total | C42: =SUM(C21:C41) -> 261.5033 | D42: =SUM(D21:D41) -> 1

Sheet Scope3_Screening
A1: Scope 3 screening (15 categories)
A2: Decide which categories are relevant, and explain every exclusion. Emissions are pulled from Activity_Data.
A5: Category | B5: Relevant? | C5: Rationale (why relevant or excluded) | D5: Est. significance | E5: Data availability | F5: Quantified in inventory? | G5: tCO2e
A6: =Lists!A7 -> 1. Purchased goods and services | B6: Yes | C6: Main category for a manufacturer: metals, components and packaging. Not quantified in this version; needs purchase data and spend-based or supplier factors. | D6: High | E6: Partial | F6: =IF(G6>0,"Yes","No") -> No | G6: =SUMIFS(Activity_Data!$K$6:$K$45,Activity_Data!$B$6:$B$45,3,Activity_Data!$C$6:$C$45,A6) -> 0
A7: =Lists!A8 -> 2. Capital goods | B7: Partly | C7: Machinery purchases are lumpy from year to year. Not quantified. | D7: Medium | E7: Partial | F7: =IF(G7>0,"Yes","No") -> No | G7: =SUMIFS(Activity_Data!$K$6:$K$45,Activity_Data!$B$6:$B$45,3,Activity_Data!$C$6:$C$45,A7) -> 0
A8: =Lists!A9 -> 3. Fuel- and energy-related activities | B8: Yes | C8: Upstream emissions of fuels and electricity, and grid losses. Not quantified; factors exist in the UK government set (well-to-tank) but were not retrieved. | D8: Medium | E8: Partial | F8: =IF(G8>0,"Yes","No") -> No | G8: =SUMIFS(Activity_Data!$K$6:$K$45,Activity_Data!$B$6:$B$45,3,Activity_Data!$C$6:$C$45,A8) -> 0
A9: =Lists!A10 -> 4. Upstream transportation and distribution | B9: Yes | C9: Inbound freight of materials. Not quantified; needs tonne-km from logistics providers. | D9: Medium | E9: Partial | F9: =IF(G9>0,"Yes","No") -> No | G9: =SUMIFS(Activity_Data!$K$6:$K$45,Activity_Data!$B$6:$B$45,3,Activity_Data!$C$6:$C$45,A9) -> 0
A10: =Lists!A11 -> 5. Waste generated in operations | B10: Yes | C10: Production waste and scrap handled by contractors. Not quantified; waste records exist by stream. | D10: Low | E10: Partial | F10: =IF(G10>0,"Yes","No") -> No | G10: =SUMIFS(Activity_Data!$K$6:$K$45,Activity_Data!$B$6:$B$45,3,Activity_Data!$C$6:$C$45,A10) -> 0
A11: =Lists!A12 -> 6. Business travel | B11: Yes | C11: Quantified: short-haul economy flights from the travel agency report (passenger-km). | D11: Medium | E11: Good | F11: =IF(G11>0,"Yes","No") -> Yes | G11: =SUMIFS(Activity_Data!$K$6:$K$45,Activity_Data!$B$6:$B$45,3,Activity_Data!$C$6:$C$45,A11) -> 22.6368
A12: =Lists!A13 -> 7. Employee commuting | B12: Yes | C12: Quantified: car commuting estimated from a survey of 60 of 200 employees and extrapolated. | D12: Medium | E12: Partial | F12: =IF(G12>0,"Yes","No") -> Yes | G12: =SUMIFS(Activity_Data!$K$6:$K$45,Activity_Data!$B$6:$B$45,3,Activity_Data!$C$6:$C$45,A12) -> 40.38
A13: =Lists!A14 -> 8. Upstream leased assets | B13: No | C13: No leased assets beyond the offices already inside the operational-control boundary. | D13: Low | E13: None | F13: =IF(G13>0,"Yes","No") -> No | G13: =SUMIFS(Activity_Data!$K$6:$K$45,Activity_Data!$B$6:$B$45,3,Activity_Data!$C$6:$C$45,A13) -> 0
A14: =Lists!A15 -> 9. Downstream transportation and distribution | B14: Partly | C14: Customers usually arrange delivery; small share paid by the company. Not quantified. | D14: Low | E14: Partial | F14: =IF(G14>0,"Yes","No") -> No | G14: =SUMIFS(Activity_Data!$K$6:$K$45,Activity_Data!$B$6:$B$45,3,Activity_Data!$C$6:$C$45,A14) -> 0
A15: =Lists!A16 -> 10. Processing of sold products | B15: No | C15: Parts are shipped as components; downstream processing is not known and is excluded. | D15: Low | E15: None | F15: =IF(G15>0,"Yes","No") -> No | G15: =SUMIFS(Activity_Data!$K$6:$K$45,Activity_Data!$B$6:$B$45,3,Activity_Data!$C$6:$C$45,A15) -> 0
A16: =Lists!A17 -> 11. Use of sold products | B16: No | C16: Components have no direct energy use in operation; use-phase is attributed to the customer's product. | D16: Low | E16: None | F16: =IF(G16>0,"Yes","No") -> No | G16: =SUMIFS(Activity_Data!$K$6:$K$45,Activity_Data!$B$6:$B$45,3,Activity_Data!$C$6:$C$45,A16) -> 0
A17: =Lists!A18 -> 12. End-of-life treatment of sold products | B17: Partly | C17: Metal parts are largely recycled at end of life; small expected effect. Not quantified. | D17: Low | E17: None | F17: =IF(G17>0,"Yes","No") -> No | G17: =SUMIFS(Activity_Data!$K$6:$K$45,Activity_Data!$B$6:$B$45,3,Activity_Data!$C$6:$C$45,A17) -> 0
... A20: =Lists!A21 -> 15. Investments | B20: No | C20: No equity or debt investments in the reporting scope. | D20: Low | E20: None | F20: =IF(G20>0,"Yes","No") -> No | G20: =SUMIFS(Activity_Data!$K$6:$K$45,Activity_Data!$B$6:$B$45,3,Activity_Data!$C$6:$C$45,A20) -> 0
A21: Total Scope 3 | G21: =SUM(G6:G20) -> 63.0168

Sheet Reduction_Scenarios
A1: Reduction roadmap (illustrative scenarios)
A2: Blue percentages are assumptions, not commitments. Baselines come from Results.
A4: Measure | B4: Scope | C4: Basis | D4: Baseline (tCO2e) | E4: Assumed reduction (%) | F4: Reduction (tCO2e) | G4: In location-based total? | H4: In market-based total? | I4: Note
A5: Renewable electricity (guarantees of origin or PPA) | B5: 2 | C5: Market-based Scope 2 | D5: =Results!B9 -> 175.905 | E5: 1 | F5: =D5*E5 -> 175.905 | G5: No | H5: Yes | I5: Assumes covered consumption has zero market-based emissions. Does not change grid emissions, so it is absent from the location-based total.
A6: Boiler efficiency and controls | B6: 1 | C6: Stationary combustion | D6: =Results!C21 -> 60.78 | E6: 0.15 | F6: =D6*E6 -> 9.117 | G6: Yes | H6: Yes | I6: Burner tuning, insulation and controls. Assumed percentage.
A7: Fleet efficiency and eco-driving | B7: 1 | C7: Mobile combustion | D7: =Results!C22 -> 31.86 | E7: 0.1 | F7: =D7*E7 -> 3.186 | G7: Yes | H7: Yes | I7: Driver training and route planning. Assumed percentage.
A8: Refrigerant leak detection and repair | B8: 1 | C8: Fugitive emissions | D8: =Results!C23 -> 15.392 | E8: 0.5 | F8: =D8*E8 -> 7.696 | G8: Yes | H8: Yes | I8: Leak checks and faster repair. Assumed percentage.
A9: Reduce air travel | B9: 3 | C9: Category 6 | D9: =Results!C32 -> 22.6368 | E9: 0.2 | F9: =D9*E9 -> 4.52736 | G9: Yes | H9: Yes | I9: Virtual meetings and rail for short trips. Assumed percentage.
A10: Commuting modal shift | B10: 3 | C10: Category 7 | D10: =Results!C33 -> 40.38 | E10: 0.2 | F10: =D10*E10 -> 8.076 | G10: Yes | H10: Yes | I10: Shuttle, public transport support and remote work. Assumed percentage.
A12: Reductions counted in location-based total | F12: =SUMIFS(F5:F10,G5:G10,"Yes") -> 32.60236
A13: Reductions counted in market-based total | F13: =SUMIFS(F5:F10,H5:H10,"Yes") -> 208.50736
A15: Basis | D15: Baseline 2025 (tCO2e) | E15: After measures (tCO2e) | F15: Reduction (%)
A16: Total, location-based | D16: =Results!B11 -> 261.5033 | E16: =D16-F12 -> 228.90094 | F16: =IF(D16=0,0,(D16-E16)/D16) -> 0.12467284
A17: Total, market-based | D17: =Results!B12 -> 346.9538 | E17: =D17-F13 -> 138.44644 | F17: =IF(D17=0,0,(D17-E17)/D17) -> 0.60096578
A20: Illustrative target check (Scope 1 + 2) | D20: Value
A21: Target year | D21: 2030
A22: Target reduction vs 2025 (market-based) | D22: 0.3
A23: Baseline Scope 1 + 2, market-based (tCO2e) | D23: =Results!B7+Results!B9 -> 283.937
A24: Target level (tCO2e) | D24: =D23*(1-D22) -> 198.7559
A25: Scope 1 + 2 after measures, market-based (tCO2e) | D25: =D23-SUMIFS(F5:F10,B5:B10,1)-F5 -> 88.033
A26: Reduction achieved, market-based | D26: =IF(D23=0,0,(D23-D25)/D23) -> 0.68995587
A27: Result | D27: =IF(D25<=D24,"Target met on market-based basis","Gap to target") -> Target met on market-based basis
A28: Baseline Scope 1 + 2, location-based (tCO2e) | D28: =Results!B7+Results!B8 -> 198.4865
A29: Scope 1 + 2 after measures, location-based (tCO2e) | D29: =D28-SUMIFS(F5:F10,B5:B10,1) -> 178.4875
A30: Reduction achieved, location-based | D30: =IF(D28=0,0,(D28-D29)/D28) -> 0.10075748
A32: The market-based target is reached mainly through renewable electricity procurement. The location-based result shows the physical reduction without it.

Sheet Controls
A1: Data controls
A2: Automated checks on the inventory. Every line should read PASS before you report.
A5: # | B5: Check | C5: Result | D5: Status | E5: What to do if CHECK
A6: 1 | B6: Rows with quantity but no Factor ID | C6: =COUNTIF(Activity_Data!$N$6:$N$45,"NO FACTOR") -> 0 | D6: =IF(ROUND(C6,6)=0,"PASS","CHECK") -> PASS | E6: Enter a Factor ID in Activity_Data.
A7: 2 | B7: Rows with a Factor ID not in Emission_Factors | C7: =COUNTIF(Activity_Data!$N$6:$N$45,"BAD FACTOR ID") -> 0 | D7: =IF(ROUND(C7,6)=0,"PASS","CHECK") -> PASS | E7: Add the factor or correct the ID.
A8: 3 | B8: Rows where unit differs from factor unit | C8: =COUNTIF(Activity_Data!$N$6:$N$45,"UNIT MISMATCH") -> 0 | D8: =IF(ROUND(C8,6)=0,"PASS","CHECK") -> PASS | E8: Convert the quantity or choose a factor with the same unit.
A9: 4 | B9: Rows missing data source or quality score | C9: =COUNTIF(Activity_Data!$N$6:$N$45,"MISSING SOURCE/DQ") -> 0 | D9: =IF(ROUND(C9,6)=0,"PASS","CHECK") -> PASS | E9: Record who provided the data and score its quality.
A10: 5 | B10: Scope 2 rows missing Location / Market method | C10: =COUNTIF(Activity_Data!$N$6:$N$45,"MISSING S2 METHOD") -> 0 | D10: =IF(ROUND(C10,6)=0,"PASS","CHECK") -> PASS | E10: Set the method in column I.
A11: 6 | B11: Rows using PLACEHOLDER factors | C11: =SUMPRODUCT((Activity_Data!$H$6:$H$45<>"")*(COUNTIFS(Emission_Factors!$A$6:$A$55,Activity_Data!$H$6:$H$45,Emission_Factors!$G$6:$G$55,"PLACEHOLDER")>0)) -> 0 | D11: =IF(ROUND(C11,6)=0,"PASS","CHECK") -> PASS | E11: Replace with a sourced factor and set Status to VERIFIED or SECONDARY.
A12: 7 | B12: Rows using SECONDARY-source factors (confirm in primary file) | C12: =SUMPRODUCT((Activity_Data!$H$6:$H$45<>"")*(COUNTIFS(Emission_Factors!$A$6:$A$55,Activity_Data!$H$6:$H$45,Emission_Factors!$G$6:$G$55,"SECONDARY")>0)) -> 3 | D12: =IF(ROUND(C12,6)=0,"PASS","CONFIRM") -> CONFIRM | E12: Open the official dataset, confirm the value and year, then set Status to VERIFIED.
A13: 8 | B13: Scope 2 kWh: Location minus Market (should be 0) | C13: =SUMIFS(Activity_Data!$F$6:$F$45,Activity_Data!$B$6:$B$45,2,Activity_Data!$I$6:$I$45,"Location")-SUMIFS(Activity_Data!$F$6:$F$45,Activity_Data!$B$6:$B$45,2,Activity_Data!$I$6:$I$45,"Market") -> 0 | D13: =IF(ROUND(C13,6)=0,"PASS","CHECK") -> PASS | E13: Both methods must use the same consumption.
A14: 9 | B14: Row total minus scope totals (tCO2e, should be 0) | C14: =SUM(Activity_Data!$K$6:$K$45)-(Results!$B$7+Results!$B$8+Results!$B$9+Results!$B$10) -> 0 | D14: =IF(ROUND(C14,6)=0,"PASS","CHECK") -> PASS | E14: A row has a missing or invalid scope or method.
A15: 10 | B15: Rows with quantity but no scope | C15: =SUMPRODUCT((Activity_Data!$F$6:$F$45<>"")*(Activity_Data!$B$6:$B$45="")) -> 0 | D15: =IF(ROUND(C15,6)=0,"PASS","CHECK") -> PASS | E15: Set the scope in column B.
A16: 11 | B16: Scope 3 total minus screening sheet total (tCO2e) | C16: =Scope3_Screening!$G$21-Results!$B$10 -> 0 | D16: =IF(ROUND(C16,6)=0,"PASS","CHECK") -> PASS | E16: Use a category from the list for every Scope 3 row.
A17: 12 | B17: Category table total minus Results total (tCO2e) | C17: =Results!$C$42-Results!$B$11 -> 0 | D17: =IF(ROUND(C17,6)=0,"PASS","CHECK") -> PASS | E17: A row has a category not in the list.
B19: Overall status | D19: =IF(COUNTIF(D6:D17,"CHECK")>0,"REVIEW",IF(COUNTIF(D6:D17,"CONFIRM")>0,"PASS WITH NOTES","ALL PASS")) -> PASS WITH NOTES

Sheet Materiality
A1: Materiality screening (impact and financial)
A2: Illustrative scoring by the author, 1 (low) to 5 (high). A topic is material if either score reaches the threshold.
A3: Materiality threshold (score) | B3: 3
A6: ESRS topic | B6: ESRS ref | C6: Impact score (1-5) | D6: Financial score (1-5) | E6: Priority score | F6: Result | G6: Rationale / stakeholders consulted
A7: Climate change | B7: E1 | C7: 5 | D7: 4 | E7: =IF(OR(C7="",D7=""),"",MAX(C7,D7)) -> 5 | F7: =IF(E7="","",IF(E7>=$B$3,"Material","Not material")) -> Material | G7: Energy- and gas-intensive production; exposure to carbon costs and customer requests.
A8: Pollution | B8: E2 | C8: 3 | D8: 2 | E8: =IF(OR(C8="",D8=""),"",MAX(C8,D8)) -> 3 | F8: =IF(E8="","",IF(E8>=$B$3,"Material","Not material")) -> Material | G8: Air emissions and lubricants from machining; regulated through permits.
A9: Water and marine resources | B9: E3 | C9: 2 | D9: 2 | E9: =IF(OR(C9="",D9=""),"",MAX(C9,D9)) -> 2 | F9: =IF(E9="","",IF(E9>=$B$3,"Material","Not material")) -> Not material | G9: Low process water use; no high-stress site assumed.
A10: Biodiversity and ecosystems | B10: E4 | C10: 1 | D10: 1 | E10: =IF(OR(C10="",D10=""),"",MAX(C10,D10)) -> 1 | F10: =IF(E10="","",IF(E10>=$B$3,"Material","Not material")) -> Not material | G10: Urban industrial sites; no protected areas nearby (assumed).
A11: Resource use and circular economy | B11: E5 | C11: 4 | D11: 3 | E11: =IF(OR(C11="",D11=""),"",MAX(C11,D11)) -> 4 | F11: =IF(E11="","",IF(E11>=$B$3,"Material","Not material")) -> Material | G11: Metal inputs and scrap: material efficiency drives cost and supply risk.
A12: Own workforce | B12: S1 | C12: 4 | D12: 3 | E12: =IF(OR(C12="",D12=""),"",MAX(C12,D12)) -> 4 | F12: =IF(E12="","",IF(E12>=$B$3,"Material","Not material")) -> Material | G12: Manufacturing workforce: health and safety, skills and retention.
A13: Workers in the value chain | B13: S2 | C13: 3 | D13: 3 | E13: =IF(OR(C13="",D13=""),"",MAX(C13,D13)) -> 3 | F13: =IF(E13="","",IF(E13>=$B$3,"Material","Not material")) -> Material | G13: Metals and component suppliers; due-diligence expectations from customers.
A14: Affected communities | B14: S3 | C14: 2 | D14: 1 | E14: =IF(OR(C14="",D14=""),"",MAX(C14,D14)) -> 2 | F14: =IF(E14="","",IF(E14>=$B$3,"Material","Not material")) -> Not material | G14: Plant in an industrial area; limited noise and traffic effects.
A15: Consumers and end-users | B15: S4 | C15: 1 | D15: 1 | E15: =IF(OR(C15="",D15=""),"",MAX(C15,D15)) -> 1 | F15: =IF(E15="","",IF(E15>=$B$3,"Material","Not material")) -> Not material | G15: B2B components; no direct consumers.
A16: Business conduct | B16: G1 | C16: 3 | D16: 3 | E16: =IF(OR(C16="",D16=""),"",MAX(C16,D16)) -> 3 | F16: =IF(E16="","",IF(E16>=$B$3,"Material","Not material")) -> Material | G16: Supplier and customer ethics; anti-corruption policies required by large customers.
A18: Scoring guide: impact = scale, scope and irremediability of the company's effect on people or environment; financial = size and likelihood of effect on the company's cash flows, access to finance or cost of capital. Document the method in Assumptions_Log.

Sheet ESRS_E1_Map
A1: ESRS E1 (climate change): where this workbook feeds each disclosure
A2: ESRS and CSRD are under revision (EU Omnibus). Verify the current text before relying on this list.
A5: Disclosure requirement | B5: Title | C5: Workbook source | D5: Status | E5: Owner | F5: Notes
A6: E1-1 | B6: Transition plan for climate change mitigation | C6: Not in this workbook. The baseline in Results is the starting point. | D6: In progress | F6: Draft roadmap in Reduction_Scenarios; no board-approved plan.
A7: E1-2 | B7: Policies related to climate change mitigation and adaptation | C7: Not in this workbook. | D7: Not started
A8: E1-3 | B8: Actions and resources in relation to climate change policies | C8: Not in this workbook. Largest sources in Results guide where to act. | D8: In progress | F8: Measures and assumed reductions in Reduction_Scenarios.
A9: E1-4 | B9: Targets related to climate change mitigation and adaptation | C9: Base year (Boundary) and baseline emissions (Results). | D9: Data available | F9: Base year 2025 and baseline set; target in Reduction_Scenarios is illustrative, not SBTi-validated.
A10: E1-5 | B10: Energy consumption and mix | C10: Activity_Data fuel and electricity rows. Renewable share and energy conversion not yet included. | D10: In progress | F10: Fuel and electricity quantities available; energy mix and renewable share still to add.
A11: E1-6 | B11: Gross Scopes 1, 2, 3 and total GHG emissions | C11: Results rows 7-12 and the category table. | D11: Data available | F11: Scope 2 disclosed both location- and market-based; Scope 3 partial (2 of 15 categories).
A12: E1-7 | B12: GHG removals and carbon credits | C12: Not in this workbook. | D12: Not started
A13: E1-8 | B13: Internal carbon pricing | C13: Not in this workbook. | D13: Not started
A14: E1-9 | B14: Anticipated financial effects from material physical and transition risks | C14: Not in this workbook. | D14: Not started

Sheet Data_Governance
A1: Data governance register
A2: Who owns each data source, where it comes from, and how it is checked. Supports traceability and audit readiness.
A5: Data item | B5: Scope | C5: Owner (role) | D5: Source system / document | E5: Update frequency | F5: Control performed | G5: Evidence location | H5: Last reviewed
A6: Diesel purchases | B6: 1 | C6: Fleet manager | D6: Fuel delivery notes | E6: Monthly | F6: Delivery notes reconciled to supplier invoices | G6: Shared drive /ESG/2025/fuel/ | H6: 46063
A7: Natural gas consumption | B7: 1 | C7: Facilities manager | D7: Utility invoices (PDF) and ERP | E7: Monthly | F7: Invoice totals reconciled to meter readings; change above 20% month on month investigated | G7: Shared drive /ESG/2025/gas/ | H7: 46063
A8: Refrigerant top-ups | B8: 1 | C8: Maintenance lead | D8: Maintenance log and technician reports | E8: Per event | F8: Quantity checked against F-gas register | G8: Shared drive /ESG/2025/refrigerants/ | H8: 46063
A9: Electricity consumption | B9: 2 | C9: Facilities manager | D9: Utility invoices (PDF) and ERP | E9: Monthly | F9: Invoice kWh reconciled to sub-meter totals | G9: Shared drive /ESG/2025/electricity/ | H9: 46063
A10: Business flights | B10: 3 | C10: HR / travel desk | D10: Travel agency annual report | E10: Annual | F10: Passenger-km recomputed for a sample of 10 trips | G10: Shared drive /ESG/2025/travel/ | H10: 46063
A11: Employee commuting | B11: 3 | C11: HR | D11: Employee survey (60 of 200 responses) | E11: Annual | F11: Response rate and extrapolation documented in assumptions log | G11: Shared drive /ESG/2025/commuting/ | H11: 46063
A12: Emission factor library | B12: 1-3 | C12: ESG analyst | D12: ISPRA, DESNZ, IPCC publications | E12: Annual | F12: Every factor has source, year and status; SECONDARY factors flagged | G12: Emission_Factors sheet | H12: 46063
A13: Inventory model | B13: 1-3 | C13: ESG analyst | D13: This workbook | E13: Annual | F13: 12 automated checks on the Controls sheet; second-person review before release | G13: Controls sheet | H13: 46063

Sheet Assumptions_Log
A1: Assumptions log
A2: Record every estimate, proxy, exclusion and methodology choice.
A5: ID | B5: Date | C5: Assumption | D5: Rationale | E5: Estimated impact | F5: Owner | G5: Status | H5: Linked rows
A6: AS-001 | B6: 46063 | C6: Commuting distance extrapolated from a survey of 60 of 200 employees to full headcount. | D6: Full survey not available this year. | E6: Medium | F6: HR | G6: Open | H6: A-007
A7: AS-002 | B7: 46063 | C7: Diesel for fleet and generator combined into one quantity from delivery notes. | D7: Delivery notes do not split vehicles and generator. | E7: Low | F7: Fleet manager | G7: Open | H7: A-001
A8: AS-003 | B8: 46063 | C8: Market-based Scope 2 uses the ISPRA national residual mix (CO2 only, production basis) as a proxy. | D8: No supplier-specific or AIB residual mix factor available in this exercise. | E8: Medium | F8: ESG analyst | G8: Open | H8: A-005
A9: AS-004 | B9: 46063 | C9: Factor years differ: gas 2024 (latest final), electricity 2025 (preliminary). | D9: Use the latest published value for each factor. | E9: Low | F9: ESG analyst | G9: Open | H9: A-002, A-004
A10: AS-005 | B10: 46063 | C10: UK government (DESNZ) travel factors applied to Italian travel and commuting. | D10: No Italian equivalent retrieved; UK factors used as an approximation. | E10: Medium | F10: ESG analyst | G10: Open | H10: A-006, A-007
A11: AS-006 | B11: 46063 | C11: Scope 3 limited to categories 6 and 7; categories 1, 3, 4 and 5 are relevant but not quantified. | D11: Data not available in this version. | E11: High | F11: ESG analyst | G11: Open | H11: Scope3_Screening
A12: AS-007 | B12: 46063 | C12: Reduction percentages and the 2030 target in Reduction_Scenarios are illustrative assumptions. | D12: Used to show how the roadmap is built; not company commitments. | E12: Medium | F12: ESG analyst | G12: Open | H12: Reduction_Scenarios

Sheet Lists
A1: Stationary combustion | C1: litres | E1: Dropdown values used by other sheets. Edit with care.
A2: Mobile combustion | C2: m3
A3: Fugitive emissions (refrigerants) | C3: kg
A4: Process emissions | C4: kWh
A5: Purchased electricity | C5: pkm
A6: Purchased heat, steam and cooling | C6: tkm
A7: 1. Purchased goods and services | C7: tonne
A8: 2. Capital goods | C8: km
A9: 3. Fuel- and energy-related activities | C9: EUR
A10: 4. Upstream transportation and distribution
A11: 5. Waste generated in operations
A12: 6. Business travel
A13: 7. Employee commuting
A14: 8. Upstream leased assets
A15: 9. Downstream transportation and distribution
A16: 10. Processing of sold products
A17: 11. Use of sold products
A18: 12. End-of-life treatment of sold products
A19: 13. Downstream leased assets
A20: 14. Franchises
A21: 15. Investments
